odoo/addons/pms_base/README.rst
odoo/addons/pms_base/__init__.py
odoo/addons/pms_base/__manifest__.py
odoo/addons/pms_base/data/pms_amenity_type.xml
odoo/addons/pms_base/data/pms_room_type.xml
odoo/addons/pms_base/data/pms_stage.xml
odoo/addons/pms_base/data/pms_team.xml
odoo/addons/pms_base/i18n/es.po
odoo/addons/pms_base/i18n/pms_base.pot
odoo/addons/pms_base/models/__init__.py
odoo/addons/pms_base/models/pms_amenity.py
odoo/addons/pms_base/models/pms_amenity_type.py
odoo/addons/pms_base/models/pms_property.py
odoo/addons/pms_base/models/pms_room.py
odoo/addons/pms_base/models/pms_room_type.py
odoo/addons/pms_base/models/pms_service.py
odoo/addons/pms_base/models/pms_stage.py
odoo/addons/pms_base/models/pms_tag.py
odoo/addons/pms_base/models/pms_team.py
odoo/addons/pms_base/models/res_company.py
odoo/addons/pms_base/models/res_config_settings.py
odoo/addons/pms_base/models/res_partner.py
odoo/addons/pms_base/readme/CONFIGURE.rst
odoo/addons/pms_base/readme/CONTRIBUTORS.rst
odoo/addons/pms_base/readme/DESCRIPTION.rst
odoo/addons/pms_base/readme/USAGE.rst
odoo/addons/pms_base/security/ir.model.access.csv
odoo/addons/pms_base/security/ir_rule.xml
odoo/addons/pms_base/security/res_groups.xml
odoo/addons/pms_base/static/description/icon.png
odoo/addons/pms_base/static/description/index.html
odoo/addons/pms_base/views/menu.xml
odoo/addons/pms_base/views/pms_amenity.xml
odoo/addons/pms_base/views/pms_amenity_type.xml
odoo/addons/pms_base/views/pms_property.xml
odoo/addons/pms_base/views/pms_room.xml
odoo/addons/pms_base/views/pms_room_type.xml
odoo/addons/pms_base/views/pms_service.xml
odoo/addons/pms_base/views/pms_stage.xml
odoo/addons/pms_base/views/pms_tag.xml
odoo/addons/pms_base/views/pms_team.xml
odoo/addons/pms_base/views/res_config_settings.xml
odoo/addons/pms_base/views/res_partner_view.xml
odoo14_addon_pms_base-14.0.1.1.1.dist-info/METADATA
odoo14_addon_pms_base-14.0.1.1.1.dist-info/WHEEL
odoo14_addon_pms_base-14.0.1.1.1.dist-info/top_level.txt
odoo14_addon_pms_base-14.0.1.1.1.dist-info/RECORD
